shaffle/__init__.py
shaffle/mapping.py
shaffle-0.0.1.dist-info/LICENSE
shaffle-0.0.1.dist-info/METADATA
shaffle-0.0.1.dist-info/WHEEL
shaffle-0.0.1.dist-info/top_level.txt
shaffle-0.0.1.dist-info/RECORD
